mace_models/__init__.py
mace_models-0.1.6.dist-info/LICENSE
mace_models-0.1.6.dist-info/METADATA
mace_models-0.1.6.dist-info/WHEEL
mace_models-0.1.6.dist-info/RECORD
