Metadata-Version: 2.1
Name: mace-models
Version: 0.1.6
Summary: Access pre-trained MACE models
Author: Rokas Elijošius
Author-email: re344@cam.ac.uk
Requires-Python: >=3.10,<4.0
Classifier: Programming Language :: Python :: 3
Classifier: Programming Language :: Python :: 3.10
Classifier: Programming Language :: Python :: 3.11
Classifier: Programming Language :: Python :: 3.12
Classifier: Programming Language :: Python :: 3.13
Requires-Dist: ase (>=3.22,<4.0)
Requires-Dist: dvc-s3 (>=3.2,<4.0)
Requires-Dist: mace-torch (>=0.3,<0.4)
Requires-Dist: zntrack (>=0.8.1,<0.9.0)
Project-URL: repository, https://github.com/RokasEl/MACE-Models
